.gitlab-ci.yml
CONTRIBUTING.md
ChangeLog.md
LICENSE
Makefile
README.rst
requirements-dev.txt
requirements-test.txt
requirements.txt
setup.cfg
setup.py
tox.ini
examples/teleinfo.py
kylin/__init__.py
kylin/exceptions.py
kylin/version.py
kylin.egg-info/PKG-INFO
kylin.egg-info/SOURCES.txt
kylin.egg-info/dependency_links.txt
kylin.egg-info/pbr.json
kylin.egg-info/requires.txt
kylin.egg-info/top_level.txt
kylin.egg-info/zip-safe
kylin/tests/__init__.py
kylin/tests/test_kylin.py